moobius/__init__.py
moobius/json_utils.py
moobius/quickstart.py
moobius/types.py
moobius/core/groups.py
moobius/core/sdk.py
moobius/core/wand.py
moobius/database/database_interface.py
moobius/database/json_database.py
moobius/database/null_database.py
moobius/database/redis_database.py
moobius/database/storage.py
moobius/network/http_api_wrapper.py
moobius/network/ws_client.py
moobius-1.8.0.dist-info/METADATA
moobius-1.8.0.dist-info/WHEEL
moobius-1.8.0.dist-info/entry_points.txt
moobius-1.8.0.dist-info/top_level.txt
moobius-1.8.0.dist-info/RECORD
