Metadata-Version: 2.1
Name: moobius
Version: 1.8.0
Summary: Moobius Platform SDK
Author-email: Kevin Kostlan <sdk@moobius.app>
Project-URL: Homepage, https://github.com/groupultra/sdk-public
Project-URL: Issues, https://github.com/groupultra/sdk-public/issues
Classifier: Programming Language :: Python :: 3
Classifier: License :: OSI Approved :: MIT License
Classifier: Operating System :: OS Independent
Requires-Python: >=3.10
Requires-Dist: aiohttp >=3.9.1
Requires-Dist: aioprocessing >=2.0.1
Requires-Dist: APScheduler >=3.10.4
Requires-Dist: dacite >=1.8.1
Requires-Dist: Requests >=2.31.0
Requires-Dist: websockets >=12.0
Requires-Dist: loguru >=0.7.2
Requires-Dist: fsspec >=2023.6.0
